mypwd/__init__.py
mypwd/__main__.py
mypwd/cli.py
mypwd/impl.py
mypwd/mypwd_error.py
mypwd-0.8.0.dist-info/METADATA
mypwd-0.8.0.dist-info/WHEEL
mypwd-0.8.0.dist-info/entry_points.txt
mypwd-0.8.0.dist-info/licenses/LICENSE
mypwd-0.8.0.dist-info/RECORD
