Metadata-Version: 2.4
Name: mypwd
Version: 0.8.0
Summary: Very simple password vault for Python projects
Project-URL: Homepage, https://github.com/berk76/mypwd
Project-URL: Repository, https://github.com/berk76/mypwd
Project-URL: Issues, https://github.com/berk76/mypwd/issues
Author-email: Jaroslav Beran <jaroslav.beran@gmail.com>
License-Expression: GPL-3.0
License-File: LICENSE
Requires-Python: >=3.6
